asgi_signing_middleware/__init__.py
asgi_signing_middleware/cookie.py
asgi_signing_middleware/tests/__init__.py
asgi_signing_middleware/tests/tests_cookie_fastapi.py
asgi_signing_middleware/tests/tests_cookie_starlette.py
asgi_signing_middleware/tests/tests_cookie_starlite.py
asgi_signing_middleware/types.py
asgi_signing_middleware-0.2.0.dist-info/LICENSE
asgi_signing_middleware-0.2.0.dist-info/WHEEL
asgi_signing_middleware-0.2.0.dist-info/METADATA
asgi_signing_middleware-0.2.0.dist-info/RECORD
