Metadata-Version: 2.1
Name: asgi-signing-middleware
Version: 0.2.0
Summary: A library that provides signing middlewares for any ASGI application.
Home-page: https://gitlab.com/hackancuba/asgi-signing-middleware
License: MPL-2.0
Author: HacKan
Author-email: hackan@gmail.com
Requires-Python: >=3.8,<4.0
Classifier: Development Status :: 1 - Planning
Classifier: Intended Audience :: Developers
Classifier: License :: OSI Approved
Classifier: License :: OSI Approved :: Mozilla Public License 2.0 (MPL 2.0)
Classifier: Natural Language :: English
Classifier: Operating System :: POSIX :: Linux
Classifier: Programming Language :: Python :: 3
Classifier: Programming Language :: Python :: 3 :: Only
Classifier: Programming Language :: Python :: 3.10
Classifier: Programming Language :: Python :: 3.8
Classifier: Programming Language :: Python :: 3.9
Classifier: Topic :: Security :: Cryptography
Classifier: Topic :: Software Development :: Libraries :: Python Modules
Classifier: Typing :: Typed
Requires-Dist: blake2signer (>=2.1.0,<3.0.0)
Requires-Dist: starlette (>=0.17.1,<0.18.0)
Project-URL: Documentation, https://asgi-signing-middleware.hackan.net
Project-URL: Repository, https://gitlab.com/hackancuba/asgi-signing-middleware
